MANIFEST.in
README.rst
setup.py
collective/__init__.py
collective.js.knockout.egg-info/PKG-INFO
collective.js.knockout.egg-info/SOURCES.txt
collective.js.knockout.egg-info/dependency_links.txt
collective.js.knockout.egg-info/entry_points.txt
collective.js.knockout.egg-info/namespace_packages.txt
collective.js.knockout.egg-info/not-zip-safe
collective.js.knockout.egg-info/requires.txt
collective.js.knockout.egg-info/top_level.txt
collective/js/__init__.py
collective/js/knockout/__init__.py
collective/js/knockout/configure.zcml
collective/js/knockout/Extensions/install.py
collective/js/knockout/profiles/default/jsregistry.xml
collective/js/knockout/profiles/default/metadata.xml
collective/js/knockout/profiles/uninstall/jsregistry.xml
collective/js/knockout/resources/knockout.js
collective/js/knockout/resources/knockout.min.js
docs/HISTORY.rst
docs/INSTALL.txt
docs/LICENSE.GPL
docs/LICENSE.txt