Metadata-Version: 1.0
Name: collective.js.knockout
Version: 3.2.0
Summary: knockout.js integration for Plone
Home-page: https://github.com/collective/collective.js.knockout
Author: RedTurtle Technology
Author-email: sviluppoplone@redturtle.it
License: GPL
Keywords: plone knockout.js javascript
Platform: UNKNOWN
Classifier: Framework :: Plone
Classifier: License :: OSI Approved :: GNU General Public License (GPL)
Classifier: Intended Audience :: Developers
Classifier: Programming Language :: Python
Classifier: Programming Language :: JavaScript
